tradezero_api/__init__.py
tradezero_api/account.py
tradezero_api/enums.py
tradezero_api/main.py
tradezero_api/notification.py
tradezero_api/portfolio.py
tradezero_api/time_helpers.py
tradezero_api/watchlist.py
tradezero_api-0.3.1.dist-info/LICENSE
tradezero_api-0.3.1.dist-info/METADATA
tradezero_api-0.3.1.dist-info/WHEEL
tradezero_api-0.3.1.dist-info/RECORD
