Metadata-Version: 2.1
Name: tradezero-api
Version: 0.3.1
Summary: A package for executing orders and retrieving data through the TradeZero web platform
Home-page: https://github.com/shner-elmo/db-wrapper
License: MIT
Author: shner-elmo
Author-email: 770elmo@gmail.com
Requires-Python: >=3.9
Classifier: Environment :: Console
Classifier: License :: OSI Approved :: MIT License
Classifier: Operating System :: OS Independent
Classifier: Programming Language :: Python
Classifier: Programming Language :: Python :: 3
Classifier: Programming Language :: Python :: 3.9
Classifier: Programming Language :: Python :: 3.10
Classifier: Programming Language :: Python :: 3.11
Classifier: Programming Language :: Python :: 3 :: Only
Requires-Dist: lxml (>=4.9.2,<5.0.0)
Requires-Dist: pandas (>=1.5.3,<2.0.0)
Requires-Dist: pytz (>=2022.7.1,<2023.0.0)
Requires-Dist: selenium (>=4.8.2,<5.0.0)
Requires-Dist: termcolor (>=2.2.0,<3.0.0)
Requires-Dist: webdriver-manager (>=3.8.5,<4.0.0)
Project-URL: Documentation, https://github.com/shner-elmo/tradezero-api/blob/master/README.md
Project-URL: Repository, https://github.com/shner-elmo/db-wrapper
Project-URL: issues, https://github.com/shner-elmo/tradezero-api/issues
